<?xml version="1.0" encoding="UTF-8"?>
<meta
  xmlns="http://exist-db.org/xquery/repo">
  <description>JMMC applications's latest releases</description>
  <author>JMMC Tech Group</author>
  <website>https://www.jmmc.fr</website>
  <status>alpha</status>
  <license>AGPL-3.0</license>
  <copyright>true</copyright>
  <type>application</type>
  <target>releases</target>
  <prepare>pre-install.xq</prepare>
  <finish>post-install.xq</finish>
  <changelog>
         <change xmlns="" version="1.1.1">
           <h3>Protection and release notes setup 2022-12-05</h3>
           <ul>
             <li>Store release notes in repo.xml</li>
             <li>Setup a robots.txt</li>
             <li>Fix some typos</li>
           </ul>
         </change>
    </changelog>

</meta>
